src/__init__.py
src/managers.py
src/models.py
src/server.py
iflow_mcp_dlwjdtn535_mcp_server-0.1.0.dist-info/METADATA
iflow_mcp_dlwjdtn535_mcp_server-0.1.0.dist-info/WHEEL
iflow_mcp_dlwjdtn535_mcp_server-0.1.0.dist-info/entry_points.txt
iflow_mcp_dlwjdtn535_mcp_server-0.1.0.dist-info/RECORD
