Metadata-Version: 2.4
Name: iflow-mcp_dlwjdtn535_mcp-server
Version: 0.1.0
Summary: MCP Chrome Integration - enables AI models to control Chrome browser and perform web automation via WebSocket
Requires-Python: >=3.12
Requires-Dist: fastapi>=0.115.12
Requires-Dist: fastmcp>=2.1.2
Requires-Dist: mcp[cli]>=1.6.0
Requires-Dist: psutil>=5.9.0
Requires-Dist: uvicorn>=0.34.0
Requires-Dist: websockets>=15.0.1
